LICENSE
README.md
cata.gz
pyproject.toml
setup.py
cata/__main__.py
cata/calendars.py
cata/colors.py
cata/configuration.py
cata/controls.py
cata/data.py
cata/dialogues.py
cata/errors.py
cata/importers.py
cata/loaders.py
cata/savers.py
cata/screen.py
cata/weather.py
cata/translations/en.py
cata/translations/ru.py
catask.egg-info/PKG-INFO
catask.egg-info/SOURCES.txt
catask.egg-info/dependency_links.txt
catask.egg-info/entry_points.txt
catask.egg-info/requires.txt
catask.egg-info/top_level.txt