Metadata-Version: 2.1
Name: catask
Version: 3.0.1
Summary: Modern TUI calendar and task manager
Home-page: https://github.com/temiksvyatov/cata
Author: Artem Svyatov
Author-email: temiksvyatov@gmail.com
License: MIT
Classifier: Development Status :: 4 - Beta
Classifier: License :: OSI Approved :: MIT License
Classifier: Environment :: Console
Classifier: Natural Language :: English
Classifier: Operating System :: OS Independent
Classifier: Programming Language :: Python :: 3.7
Classifier: Programming Language :: Python :: 3.8
Classifier: Programming Language :: Python :: 3.9
Classifier: Programming Language :: Python :: 3.10
Classifier: Topic :: Utilities
Requires-Python: ~=3.7
License-File: LICENSE
Requires-Dist: holidays
Requires-Dist: jdatetime
Requires-Dist: icalendar
Requires-Dist: taskw
